simplemaze/__init__.py
simplemaze-0.1.1.dist-info/METADATA
simplemaze-0.1.1.dist-info/WHEEL
simplemaze-0.1.1.dist-info/top_level.txt
simplemaze-0.1.1.dist-info/RECORD
